app/__init__.py
app/__main__.py
app/config.py
app/controllers/__init__.py
app/controllers/base_controller.py
app/controllers/storage_controller.py
app/services/__init__.py
app/services/helper_service.py
app/services/rancher_service.py
app/services/storage_service.py
lasso_cli-0.0.1.dist-info/DESCRIPTION.rst
lasso_cli-0.0.1.dist-info/METADATA
lasso_cli-0.0.1.dist-info/RECORD
lasso_cli-0.0.1.dist-info/WHEEL
lasso_cli-0.0.1.dist-info/entry_points.txt
lasso_cli-0.0.1.dist-info/metadata.json
lasso_cli-0.0.1.dist-info/top_level.txt
