Metadata-Version: 2.0
Name: lasso-cli
Version: 0.0.1
Summary: A cli helper for rancher
Home-page: https://lasso.jamrizzi.com
Author: Jam Risser
Author-email: jam@jamrizzi.com
License: MIT
Keywords: cli foundation sync symlink command line interface cement
Platform: UNKNOWN
Classifier: Development Status :: 4 - Beta
Classifier: Intended Audience :: Developers
Classifier: Topic :: Utilities
Classifier: License :: OSI Approved :: MIT License
Classifier: Programming Language :: Python :: 2
Classifier: Programming Language :: Python :: 2.7
Classifier: Programming Language :: Python :: 3
Classifier: Programming Language :: Python :: 3.3
Classifier: Programming Language :: Python :: 3.4
Classifier: Programming Language :: Python :: 3.5
Requires-Dist: argcomplete (==1.9.3)
Requires-Dist: cement (==2.10.2)
Requires-Dist: certifi (==2017.11.5)
Requires-Dist: cfoundation (==0.1.0)
Requires-Dist: chardet (==3.0.4)
Requires-Dist: future (==0.16.0)
Requires-Dist: gdapi-python (==0.5.3)
Requires-Dist: idna (==2.6)
Requires-Dist: pydash (==4.3.0)
Requires-Dist: requests (==2.18.4)
Requires-Dist: six (==1.11.0)
Requires-Dist: urllib3 (==1.22)
